django_unmanaged_assistant/__init__.py
django_unmanaged_assistant/apps.py
django_unmanaged_assistant/management/__init__.py
django_unmanaged_assistant/management/__pycache__/__init__.cpython-312.pyc
django_unmanaged_assistant/management/commands/__init__.py
django_unmanaged_assistant/management/commands/create_databases.py
django_unmanaged_assistant/management/commands/create_unmanaged_tables.py
django_unmanaged_assistant/management/commands/__pycache__/__init__.cpython-312.pyc
django_unmanaged_assistant/management/commands/__pycache__/create_unmanaged_tables.cpython-312.pyc
django_unmanaged_assistant-2024.10.28.1.dist-info/LICENSE.txt
django_unmanaged_assistant-2024.10.28.1.dist-info/METADATA
django_unmanaged_assistant-2024.10.28.1.dist-info/WHEEL
django_unmanaged_assistant-2024.10.28.1.dist-info/top_level.txt
django_unmanaged_assistant-2024.10.28.1.dist-info/RECORD
