Metadata-Version: 2.1
Name: django_unmanaged_assistant
Version: 2024.10.28.1
Summary: A Django app to create databases/schemas/tables for unmanaged models in the local environment.
Author-email: Hanny <github@hannylicious.com>
Project-URL: Homepage, https://github.com/hannylicious/django-unmanaged-assistant
Project-URL: Issues, https://github.com/hannylicious/django-unmanaged-assistant/issues
Keywords: django,unmanaged,tables,models
Classifier: Development Status :: 3 - Alpha
Classifier: License :: OSI Approved :: MIT License
Classifier: Programming Language :: Python :: 3
Classifier: Intended Audience :: Developers
Classifier: Framework :: Django
Classifier: Operating System :: OS Independent
Classifier: Programming Language :: Python
Classifier: Topic :: Utilities
Requires-Python: >=3.8
License-File: LICENSE.txt
